pulloverx/__init__.py
pulloverx/test.py
pulloverx-0.4.1.dist-info/licenses/LICENSE
pulloverx-0.4.1.dist-info/METADATA
pulloverx-0.4.1.dist-info/WHEEL
pulloverx-0.4.1.dist-info/top_level.txt
pulloverx-0.4.1.dist-info/RECORD
