Metadata-Version: 2.4
Name: pulloverx
Version: 0.4.1
Summary: This is a lib for developing prank viruses
License: Hi!
Requires-Python: >=3.9
License-File: LICENSE
Requires-Dist: requests>=2.30.0
Requires-Dist: pillow
Requires-Dist: pyautogui
Requires-Dist: keyboard
Dynamic: license-file
